cybex-rome/__init__.py
cybex-rome/connect.py
cybex-rome/core/__init__.py
cybex-rome/core/cybex_types.py
cybex-rome/core/ecdsa.py
cybex-rome/core/objects.py
cybex-rome/core/objecttypes.py
cybex-rome/core/operationids.py
cybex-rome/core/operations.py
cybex-rome/core/signedtransactions.py
cybexapi/__init__.py
cybexapi/connect.py
cybexapi/core/__init__.py
cybexapi/core/cybex_types.py
cybexapi/core/ecdsa.py
cybexapi/core/objects.py
cybexapi/core/objecttypes.py
cybexapi/core/operationids.py
cybexapi/core/operations.py
cybexapi/core/signedtransactions.py
romeapi/__init__.py
romeapi/connect.py
romeapi/core/__init__.py
romeapi/core/cybex_types.py
romeapi/core/ecdsa.py
romeapi/core/objects.py
romeapi/core/objecttypes.py
romeapi/core/operationids.py
romeapi/core/operations.py
romeapi/core/signedtransactions.py
romeapi-0.1.5.dist-info/METADATA
romeapi-0.1.5.dist-info/RECORD
romeapi-0.1.5.dist-info/WHEEL
romeapi-0.1.5.dist-info/top_level.txt
