Metadata-Version: 2.1
Name: romeapi
Version: 0.1.5
Summary: API connector to CYBEX exchange, the first realtime order matching decentralized exchange
Home-page: https://github.com/CybexDex/RomeAPI.git
Author: CYBEX team
Author-email: ruoshui.lu@cybex.io
License: UNKNOWN
Project-URL: Main, https://cybex.io
Project-URL: Cybex Open Source, https://github.com/CybexDex
Project-URL: Source, https://github.com/CybexDex/RomeAPI.git
Keywords: crypto exchange api development
Platform: UNKNOWN
Classifier: Development Status :: 3 - Alpha
Classifier: Intended Audience :: Developers
Classifier: Topic :: Software Development :: Build Tools
Classifier: License :: OSI Approved :: MIT License
Classifier: Programming Language :: Python :: 3
Classifier: Programming Language :: Python :: 3.5
Classifier: Programming Language :: Python :: 3.6
Classifier: Programming Language :: Python :: 3.7
Requires-Python: !=3.0.*, !=3.1.*, !=3.2.*, !=3.3.*, <4
Requires-Dist: requests
Requires-Dist: coincurve
Requires-Dist: graphenelib (==0.6.1)
